django_admin_auth_emailpin/__init__.py
django_admin_auth_emailpin/models.py
django_admin_auth_emailpin-1.0.dist-info/LICENSE
django_admin_auth_emailpin-1.0.dist-info/METADATA
django_admin_auth_emailpin-1.0.dist-info/WHEEL
django_admin_auth_emailpin-1.0.dist-info/top_level.txt
django_admin_auth_emailpin-1.0.dist-info/RECORD
