Metadata-Version: 2.1
Name: django-admin-auth-emailpin
Version: 1.0
Summary: Authorization for Django admin through one-time codes sent by email.
Home-page: https://github.com/vb64/django.admin.auth.emailpin
Author: Vitaly Bogomolov
Author-email: mail@vitaly-bogomolov.ru
License: UNKNOWN
Project-URL: Bug Tracker, https://github.com/vb64/django.admin.auth.emailpin/issues
Platform: UNKNOWN
Classifier: Programming Language :: Python :: 3
Classifier: License :: OSI Approved :: MIT License
Classifier: Operating System :: OS Independent
Requires-Python: >=3.6
